setup.py
contenteditable/__init__.py
contenteditable/models.py
contenteditable/urls.py
contenteditable/utils.py
contenteditable/views.py
django_contenteditable.egg-info/PKG-INFO
django_contenteditable.egg-info/SOURCES.txt
django_contenteditable.egg-info/dependency_links.txt
django_contenteditable.egg-info/top_level.txt
sample/__init__.py
sample/manage.py
sample/settings.py
sample/urls.py