Metadata-Version: 1.0
Name: django-contenteditable
Version: 0.1
Summary: Django support for HTML contenteditable
Home-page: https://github.com/lusentis/django-contenteditable
Author: Simone Lusenti
Author-email: simone@slusenti.me
License: GPL
Keywords: django contenteditable
Platform: UNKNOWN
Classifier: Development Status :: 5 - Production/Stable
Classifier: License :: OSI Approved :: GNU General Public License (GPL)
